bonding/__init__.py
bonding/amms/__init__.py
bonding/amms/allamms.py
bonding/amms/ammdefaultparams.py
bonding/amms/bondingcurveamm.py
bonding/amms/expbondingcurveamm.py
bonding/amms/growthbondingcurveamm.py
bonding/amms/linearbondingcurveamm.py
bonding/amms/logbondingcurveamm.py
bonding/amms/sqrtbondingcurveamm.py
bonding/curveplots/__init__.py
bonding/curveplots/matplotlibcurveplot.py
bonding/curves/__init__.py
bonding/curves/allcurves.py
bonding/curves/bondingcurve.py
bonding/curves/expbondingcurve.py
bonding/curves/growthbondingcurve.py
bonding/curves/linearbondingcurve.py
bonding/curves/logbondingcurve.py
bonding/curves/sqrtbondingcurve.py
bonding/curves/verifyintegralaccuracy.py
bonding/using/__init__.py
bonding/using/usingmatplotlib.py
bonding/using/usingscipy.py
bonding-0.0.5.dist-info/LICENSE
bonding-0.0.5.dist-info/METADATA
bonding-0.0.5.dist-info/WHEEL
bonding-0.0.5.dist-info/entry_points.txt
bonding-0.0.5.dist-info/top_level.txt
bonding-0.0.5.dist-info/RECORD
